MANIFEST.in
README.txt
setup.py
ADISON.egg-info/PKG-INFO
ADISON.egg-info/SOURCES.txt
ADISON.egg-info/dependency_links.txt
ADISON.egg-info/top_level.txt
twine/__init__.py
twine/__main__.py
twine/auth.py
twine/cli.py
twine/exceptions.py
twine/package.py
twine/repository.py
twine/settings.py
twine/utils.py
twine/wheel.py
twine/wininst.py
twine/commands/__init__.py
twine/commands/check.py
twine/commands/register.py
twine/commands/upload.py