Metadata-Version: 2.1
Name: ADISON
Version: 0.0.1
Summary: An AI made bot named ADISON which have 50+ features
Home-page: UNKNOWN
Author: Jiya Khetami
Author-email: jiya.khetani1742@gmail.com
License: MIT
Keywords: calculator
Platform: UNKNOWN
Classifier: Development Status :: 5 - Production/Stable
Classifier: Intended Audience :: Education
Classifier: Operating System :: Microsoft :: Windows :: Windows 10
Classifier: License :: OSI Approved :: MIT License
Classifier: Programming Language :: Python :: 3
